p_winds/__init__.py
p_winds/carbon.py
p_winds/energetics.py
p_winds/helium.py
p_winds/hydrogen.py
p_winds/lines.py
p_winds/microphysics.py
p_winds/oxygen.py
p_winds/parker.py
p_winds/tools.py
p_winds/transit.py
p_winds-1.4.7.dist-info/LICENSE
p_winds-1.4.7.dist-info/METADATA
p_winds-1.4.7.dist-info/WHEEL
p_winds-1.4.7.dist-info/top_level.txt
p_winds-1.4.7.dist-info/RECORD
