Metadata-Version: 2.1
Name: p_winds
Version: 1.4.7
Summary: Parker wind models for planetary atmospheres
Home-page: https://github.com/ladsantos/p-winds
Author: Leonardo dos Santos
Author-email: ldsantos@stsci.edu
License: MIT
Classifier: Development Status :: 5 - Production/Stable
Classifier: Intended Audience :: Science/Research
Classifier: License :: OSI Approved :: MIT License
Classifier: Operating System :: OS Independent
Classifier: Programming Language :: Python
License-File: LICENSE
Requires-Dist: numpy
Requires-Dist: scipy >=1.5
Requires-Dist: astropy
Requires-Dist: flatstar
